token_utils.py
token_utils-0.1.8.dist-info/LICENSE
token_utils-0.1.8.dist-info/METADATA
token_utils-0.1.8.dist-info/WHEEL
token_utils-0.1.8.dist-info/top_level.txt
token_utils-0.1.8.dist-info/RECORD
