Metadata-Version: 2.1
Name: token-utils
Version: 0.1.8
Summary: Small utility to work with Python tokens
Home-page: https://github.com/aroberge/token-utils
Author: André Roberge
Author-email: Andre.Roberge@gmail.com
License: UNKNOWN
Platform: UNKNOWN
Classifier: Development Status :: 1 - Planning
Classifier: License :: OSI Approved :: MIT License
Classifier: Programming Language :: Python :: 3
Classifier: Programming Language :: Python :: 3.6
Classifier: Programming Language :: Python :: 3.7
Classifier: Programming Language :: Python :: 3.8
Requires-Python: >=3.6
